devtools_duplicate_remover/__init__.py
devtools_duplicate_remover-1.0.1.dist-info/METADATA
devtools_duplicate_remover-1.0.1.dist-info/WHEEL
devtools_duplicate_remover-1.0.1.dist-info/top_level.txt
devtools_duplicate_remover-1.0.1.dist-info/RECORD
