Metadata-Version: 2.1
Name: devtools-duplicate-remover
Version: 1.0.1
Summary: Duplicate line remover
Home-page: https://devtools.at/tools/duplicate-remover
Author: DevTools.at
Author-email: hello@devtools.at
Project-URL: Homepage, https://devtools.at/tools/duplicate-remover
Project-URL: Repository, https://github.com/devtools-at/duplicate-remover
Classifier: Development Status :: 4 - Beta
Classifier: Intended Audience :: Developers
Classifier: License :: OSI Approved :: MIT License
Classifier: Programming Language :: Python :: 3
Requires-Python: >=3.8
